Topsis/__init__.py
Topsis/topsis.py
102003759-0.0.1.dist-info/METADATA
102003759-0.0.1.dist-info/WHEEL
102003759-0.0.1.dist-info/entry_points.txt
102003759-0.0.1.dist-info/top_level.txt
102003759-0.0.1.dist-info/RECORD
